{
  "packageName": "SolArk Inverter",
  "author": "StarkTemplar",
  "version": "0.5.2",
  "minimumHEVersion": "0.0",
  "dateReleased": "2025-02-01",
  "documentationLink": "https://github.com/StarkTemplar/Hubitat/tree/main/Solar",
  "communityLink": "https://community.hubitat.com/t/solark-sunsynk-inverter-api-link/125050",
  "releaseNotes": "Version [0.5.2] - 2025-02-01\n  - Highlight grid number when grid presence is not present.",
  "drivers": [
    {
      "id": "6ab0b85a-c9ed-4c21-af13-e29461125cdd",
      "name": "SolArk Inverter",
      "namespace": "StarkTemplar",
      "location": "https://raw.githubusercontent.com/StarkTemplar/Hubitat/refs/heads/main/Solar/SolArk_Inverter.groovy",
      "required": true
    }
  ]
}